security_cli/__init__.py
security_cli/__main__.py
security_cli/action.py
security_cli/base.py
security_cli/config.py
security_cli/data/templates/abuseipdb.ipaddress.jinja2
security_cli/data/templates/alienvault.domain.jinja2
security_cli/data/templates/alienvault.ipaddress.jinja2
security_cli/data/templates/hibp.email.jinja2
security_cli/data/templates/hybridanalysis.domain.jinja2
security_cli/data/templates/hybridanalysis.ipaddress.jinja2
security_cli/data/templates/shodan.domain.jinja2
security_cli/data/templates/shodan.ipaddress.jinja2
security_cli/data/templates/urlscan.domain.jinja2
security_cli/data/templates/urlscan.ipaddress.jinja2
security_cli/data/templates/urlscan.url.jinja2
security_cli/data/templates/virustotal.domain.jinja2
security_cli/data/templates/virustotal.ipaddress.jinja2
security_cli/enrich.py
security_cli/logger.py
security_cli/observable.py
security_cli/services/__init__.py
security_cli/services/abuseipdb.py
security_cli/services/alienvault.py
security_cli/services/base.py
security_cli/services/hibp.py
security_cli/services/hybridanalysis.py
security_cli/services/shodan.py
security_cli/services/urlscan.py
security_cli/services/virustotal.py
security_cli-0.1.0.dist-info/METADATA
security_cli-0.1.0.dist-info/WHEEL
security_cli-0.1.0.dist-info/entry_points.txt
security_cli-0.1.0.dist-info/RECORD
