Metadata-Version: 2.3
Name: security-cli
Version: 0.1.0
Summary: 
Author: MSAdministrator
Author-email: 10687261+MSAdministrator@users.noreply.github.com
Requires-Python: >=3.13
Classifier: Programming Language :: Python :: 3
Classifier: Programming Language :: Python :: 3.13
Requires-Dist: black (>=25.1.0,<26.0.0)
Requires-Dist: cattrs (>=24.1.3)
Requires-Dist: fire (>=0.7.0)
Requires-Dist: httpx (>=0.28.1)
Requires-Dist: jinja2 (>=3.1.6)
Requires-Dist: pyyaml (>=6.0.2)
Requires-Dist: requests (>=2.32.3)
